examples/__init__.py
examples/attack_txt2img_pipeline.py
examples/eval_gpt2.py
examples/eval_gpt2_with_attack_enhanced_prompt.py
tests/__init__.py
yijian_community/__init__.py
yijian_community/data/__init__.py
yijian_community/data/data_utils.py
yijian_community/defense/__init__.py
yijian_community/defense/image_defense.py
yijian_community/defense/text_defense.py
yijian_community/evaluator/__init__.py
yijian_community/evaluator/metrics.py
yijian_community/evaluator/tagger.py
yijian_community/model/__init__.py
yijian_community/model/api_infer.py
yijian_community/model/base_infer.py
yijian_community/model/hf_infer.py
yijian_community/technique/__init__.py
yijian_community/technique/prompt_attack.py
yijian_community/technique/txt2img_seeds/__init__.py
yijian_community/technique/txt2img_seeds/fallacious_premise.py
yijian_community/technique/txt2img_seeds/info_compression.py
yijian_community/technique/txt2img_seeds/info_expansion.py
yijian_community/technique/txt2img_seeds/keyword_extraction.py
yijian_community/technique/txt2img_seeds/reverse_induction.py
yijian_community/technique/txt2txt_seeds/__init__.py
yijian_community/technique/txt2txt_seeds/code_attack.py
yijian_community/technique/txt2txt_seeds/fallacious_premise.py
yijian_community/technique/txt2txt_seeds/forced_consent.py
yijian_community/technique/txt2txt_seeds/implicit_knowledge.py
yijian_community/technique/txt2txt_seeds/introduction.py
yijian_community/technique/txt2txt_seeds/pros_and_cons.py
yijian_community/technique/txt2txt_seeds/repetition.py
yijian_community/technique/txt2txt_seeds/reverse_induction.py
yijian_community/technique/txt2txt_seeds/sentence_overflow.py
yijian_community/technique/txt2txt_seeds/step_by_step.py
yijian_community/technique/txt2txt_seeds/text_summarization.py
yijian_community/technique/txt2txt_seeds/virtualization.py
yijian_community/technique/txt2txt_seeds/writing_assistant.py
yijian_community/utils/__init__.py
yijian_community/utils/constants.py
yijian_community-0.1.4.dist-info/LICENSE
yijian_community-0.1.4.dist-info/METADATA
yijian_community-0.1.4.dist-info/WHEEL
yijian_community-0.1.4.dist-info/top_level.txt
yijian_community-0.1.4.dist-info/RECORD
