Metadata-Version: 2.1
Name: yijian-community
Version: 0.1.4
Summary: YiJian-Community
Home-page: https://acta.alipay.com/detect/security
Author: Ant Group
License: Apache 2.0
Platform: Linux
Classifier: Development Status :: 3 - Alpha
Classifier: Environment :: GPU
Classifier: Intended Audience :: Developers
Classifier: Intended Audience :: Education
Classifier: License :: OSI Approved :: Apache Software License
Classifier: Natural Language :: Chinese (Simplified)
Classifier: Natural Language :: English
Classifier: Operating System :: POSIX :: Linux
Classifier: Programming Language :: Python :: 3.10
Classifier: Programming Language :: Python :: 3.11
Classifier: Programming Language :: Python :: 3.12
Classifier: Programming Language :: Python :: 3.13
Classifier: Programming Language :: Python :: 3.14
Requires-Python: >=3.10
License-File: LICENSE
Requires-Dist: torch
Requires-Dist: vllm
Requires-Dist: torchvision
Requires-Dist: jieba
Requires-Dist: sacrebleu
Requires-Dist: bert-score
Requires-Dist: rouge-metric
Requires-Dist: sentence-transformers
Requires-Dist: pytest
Requires-Dist: diffusers
Requires-Dist: rich
Requires-Dist: einops
Requires-Dist: accelerate
Requires-Dist: timm
